dsort/__init__.py
dsort/dsort.py
dsort-0.0.1.dist-info/LICENSE
dsort-0.0.1.dist-info/METADATA
dsort-0.0.1.dist-info/WHEEL
dsort-0.0.1.dist-info/top_level.txt
dsort-0.0.1.dist-info/RECORD
