Metadata-Version: 2.1
Name: dsort
Version: 0.0.1
Summary: dsort - sorts YAML/JSON according to a configurable preference
Home-page: https://github.com/davur/dsort
Author: Davur Clementsen
Author-email: davur@davur.net
License: MIT license
Keywords: dsort
Classifier: Development Status :: 2 - Pre-Alpha
Classifier: Intended Audience :: Developers
Classifier: License :: OSI Approved :: MIT License
Classifier: Natural Language :: English
Classifier: Programming Language :: Python :: 3
Classifier: Programming Language :: Python :: 3.6
Classifier: Programming Language :: Python :: 3.7
Classifier: Programming Language :: Python :: 3.8
Requires-Python: >=3.6
License-File: LICENSE
